{
    "observations": {
        "x": [
            487,
            460,
            493,
            521,
            556,
            582,
            610,
            632,
            659,
            673,
            695,
            721,
            737,
            752,
            763,
            782,
            803,
            823,
            834,
            847,
            859,
            871,
            881,
            886,
            900,
            908,
            913,
            922,
            931,
            935,
            943,
            952,
            958,
            960,
            970,
            976,
            983,
            982,
            994,
            995,
            1000,
            1008,
            1010,
            1014,
            1014,
            1018,
            1026,
            1030,
            1042,
            1034,
            1042
        ],
        "y": [
            847,
            824,
            803,
            784,
            774,
            761,
            732,
            703,
            682,
            655,
            634,
            618,
            596,
            575,
            552,
            540,
            505,
            496,
            482,
            472,
            457,
            445,
            433,
            424,
            418,
            407,
            395,
            382,
            374,
            364,
            356,
            349,
            341,
            332,
            326,
            307,
            306,
            300,
            292,
            286,
            288,
            276,
            274,
            265,
            264,
            262,
            242,
            241,
            233,
            228,
            217
        ],
        "r": [
            56,
            67,
            65,
            64,
            64,
            63,
            61,
            57,
            56,
            60,
            54,
            57,
            51,
            49,
            44,
            48,
            39,
            43,
            44,
            43,
            41,
            41,
            39,
            40,
            35,
            33,
            36,
            36,
            35,
            34,
            34,
            33,
            33,
            32,
            31,
            30,
            30,
            29,
            30,
            29,
            23,
            29,
            28,
            27,
            26,
            20,
            27,
            25,
            35,
            22,
            20
        ],
        "f": [
            16,
            18,
            19,
            20,
            21,
            22,
            23,
            24,
            25,
            26,
            27,
            28,
            29,
            30,
            31,
            32,
            34,
            35,
            36,
            37,
            38,
            39,
            40,
            41,
            42,
            43,
            44,
            45,
            46,
            47,
            48,
            49,
            50,
            51,
            52,
            54,
            55,
            56,
            57,
            58,
            59,
            60,
            61,
            62,
            63,
            64,
            66,
            67,
            69,
            71,
            74
        ]
    },
    "estimations": {
        "x": [
            435.74450868999924,
            463.23231863320694,
            489.8382070796046,
            515.5741388410639,
            540.4523330315499,
            564.4852630671202,
            587.6856566659262,
            610.0664958482121,
            631.6410169363154,
            652.4227105546665,
            672.4253216297893,
            691.6628493903006,
            710.1495473669104,
            727.8999233924219,
            744.9287396017312,
            761.251012431828,
            776.8820126217947,
            791.8372652128073,
            806.1325495481342,
            819.7838992731381,
            832.8076023352735,
            845.2202009840892,
            857.0384917712263,
            868.27952555042,
            878.9606074774972,
            889.0992970103794,
            898.7134079090806,
            907.821008235708,
            916.4404203544616,
            924.5902209316353,
            932.2892409356157,
            939.5565656368824,
            946.4115346080082,
            952.8737417236594,
            958.9630351605952,
            964.6995173976682,
            970.1035452158233,
            975.1957296980995,
            979.9969362296288,
            984.5282844976359,
            988.8111484914389,
            992.867156502449,
            996.7181911241707,
            1000.3863892522018,
            1003.894142084232,
            1007.2640951200465,
            1010.5191481615213,
            1013.6824553126266,
            1016.7774249794261,
            1019.8277198700757,
            1022.8572569948251,
            1025.8902076660177,
            1028.950997498088,
            1032.064306407566,
            1035.255068613074,
            1038.5484726353263,
            1041.9699612971322,
            1045.5452317233924
        ],
        "y": [
            870.7112059112015,
            847.8340935850554,
            825.2266701618199,
            802.9153211693163,
            780.9250293152269,
            759.2793744870949,
            738.0005337523244,
            717.1092813581804,
            696.624988731789,
            676.5656244801368,
            656.9477543900716,
            637.7865414283023,
            619.0957457413982,
            600.88772465579,
            583.1734326777691,
            565.9624214934877,
            549.2628399689593,
            533.0814341500579,
            517.4235472625186,
            502.2931197119373,
            487.69268908377114,
            473.6233901433378,
            460.08495483581606,
            447.0757122862457,
            434.59258879952705,
            422.6311078604217,
            411.18539013355206,
            400.24815346340154,
            389.8107128743142,
            379.8629805704955,
            370.3934659360112,
            361.3892755347883,
            352.83611311061486,
            344.7182795871395,
            337.018673067872,
            329.7187888361833,
            322.79871935530457,
            316.2371542683285,
            310.0113803982082,
            304.0972817477583,
            298.46933949965376,
            293.10063201643095,
            287.96283484048683,
            283.02622069407926,
            278.2596594793272,
            273.6306182782105,
            269.1051613525698,
            264.6479501441064,
            260.22224327438346,
            255.78989654482405,
            251.3113629367126,
            246.7456926111944,
            242.0505329092756,
            237.1821283518235,
            232.0953206395659,
            226.74354865309192,
            221.07884845285116,
            215.05185327915467
        ],
        "r": [
            63.98223010412198,
            63.747404592379155,
            63.351938638066464,
            62.81094317784884,
            62.1389863871616,
            61.35009368021039,
            60.45774770997125,
            59.474888368190534,
            58.41391278538499,
            57.28667533084169,
            56.104487612618094,
            54.878118477541996,
            53.61779401121156,
            52.333197537995304,
            51.033469621032104,
            49.727208062231185,
            48.42246790227213,
            47.12676142060489,
            45.84705813544977,
            44.58978480379743,
            43.360825421408876,
            42.16552122281547,
            41.00867068131898,
            39.894529508991454,
            38.82681065667535,
            37.80868431398348,
            36.842777909298974,
            35.93117610977537,
            35.07542082133653,
            34.276511188676686,
            33.53490359526043,
            32.85051166332266,
            32.22270625386872,
            31.65031546667427,
            31.131624640285295,
            30.66437635201818,
            30.245770417959676,
            29.872463892966778,
            29.540571070667056,
            29.245663483458202,
            28.98276990250841,
            28.746376337756203,
            28.530426037910416,
            28.328319490450355,
            28.132914421625486,
            27.936525796455868,
            27.730925818731635,
            27.507343931013622,
            27.256466814632688,
            26.968438389690277,
            26.632859815058225,
            26.238789488378416,
            25.774743046063406,
            25.22869336329586,
            24.588070554029116,
            23.839761970986558,
            22.970112205662076,
            21.964923088319892
        ],
        "f": [
            16,
            17,
            18,
            19,
            20,
            21,
            22,
            23,
            24,
            25,
            26,
            27,
            28,
            29,
            30,
            31,
            32,
            33,
            34,
            35,
            36,
            37,
            38,
            39,
            40,
            41,
            42,
            43,
            44,
            45,
            46,
            47,
            48,
            49,
            50,
            51,
            52,
            53,
            54,
            55,
            56,
            57,
            58,
            59,
            60,
            61,
            62,
            63,
            64,
            65,
            66,
            67,
            68,
            69,
            70,
            71,
            72,
            73
        ]
    }
}